wowool/native/core/wowool_sdk.cpp
wowool/package/lib/_wowool_plugin.cpython-313-aarch64-linux-gnu.so
wowool/package/lib/_wowool_sdk.cpython-313-aarch64-linux-gnu.so
wowool/package/lib/afst++
wowool/package/lib/libboost_regex.dylib
wowool/package/lib/libicudata.dylib
wowool/package/lib/libicudata.so
wowool/package/lib/libicuuc.dylib
wowool/package/lib/libicuuc.so
wowool/package/lib/libwowool.3.1.2.dylib
wowool/package/lib/libwowool.so.3.1.2
wowool/package/lib/woc++
wowool/package/lib/wow++
wowool/package/lib/wowool_plugin.py
wowool/package/lib/wowool_sdk.py
wowool/plugin/wowool_plugin.cpp
wowool/plugin/wowool_plugin.hpp
wowool_sdk_cpp.libs/libicudata-30ab4584.so
wowool_sdk_cpp.libs/libicuuc-934dda5f.so
wowool_sdk_cpp.libs/libwowool-841b8f45.so.3.1.2
wowool_sdk_cpp-3.5.6.dist-info/METADATA
wowool_sdk_cpp-3.5.6.dist-info/WHEEL
wowool_sdk_cpp-3.5.6.dist-info/top_level.txt
wowool_sdk_cpp-3.5.6.dist-info/RECORD
