Metadata-Version: 2.4
Name: wowool-sdk-cpp
Version: 3.5.6
Summary: Wowool NLP Toolkit C++ SDK Python Bindings
Author: Wowool
Requires-Python: >=3.11
Dynamic: author
Dynamic: description
Dynamic: description-content-type
Dynamic: requires-python
Dynamic: summary
